pdkutil
