Metadata-Version: 1.1
Name: pdkutil
Version: 0.0.2
Summary: Stores a pdk file to a barbican container.
Home-page: https://github.com/cloudbase/pdkutil
Author: Simona Iuliana Toader
Author-email: info@cloudbasesolutions.com
License: Apache 2.0
Keywords: pdk shieldedvms
Platform: UNKNOWN
Classifier: Development Status :: 5 - Production/Stable
Classifier: Programming Language :: Python
Classifier: Programming Language :: Python :: 2
Classifier: Programming Language :: Python :: 2.7
Classifier: Programming Language :: Python :: 3
Classifier: Programming Language :: Python :: 3.4
Classifier: Programming Language :: Python :: 3.5
Classifier: License :: OSI Approved :: Apache Software License
Classifier: Topic :: System :: Systems Administration
